AR_test_module/__init__.py
AR_test_module/add.py
AR_test_module/subtract.py
AR_test_module/extras/__init__.py
AR_test_module/extras/divide.py
AR_test_module/extras/multiply.py
AR_test_module-0.0.2.dist-info/METADATA
AR_test_module-0.0.2.dist-info/WHEEL
AR_test_module-0.0.2.dist-info/top_level.txt
AR_test_module-0.0.2.dist-info/RECORD
